MANIFEST.in
README.rst
requirements.txt
setup.py
test_requirements.txt
fanart/__init__.py
fanart/core.py
fanart/errors.py
fanart/immutable.py
fanart/items.py
fanart/movie.py
fanart/music.py
fanart/tv.py
fanart/tests/__init__.py
fanart/tests/test_core.py
fanart/tests/test_immutable.py
fanart/tests/test_items.py
fanart/tests/test_movie.py
fanart/tests/test_music.py
fanart/tests/test_tv.py
python_fanart.egg-info/PKG-INFO
python_fanart.egg-info/SOURCES.txt
python_fanart.egg-info/dependency_links.txt
python_fanart.egg-info/requires.txt
python_fanart.egg-info/top_level.txt