Metadata-Version: 1.0
Name: python-fanart
Version: 1.3.0
Summary: Python interface to fanart.tv API
